[
  {
    "nis": "1",
    "name": "achmad musthofa ibrahim",
    "gender": "L",
    "title": "Anggota"
  },
  {
    "nis": "2",
    "name": "aldrin alfredo sibarani",
    "gender": "L",
    "title": ""
  },
  {
    "nis": "3",
    "name": "angelica christabel hermawan",
    "gender": "P",
    "title": "Anggota"
  },
  {
    "nis": "4",
    "name": "azkadina khansa kamania",
    "gender": "P",
    "title": "Anggota"
  },
  {
    "nis": "5",
    "name": "bintang nur afizah",
    "gender": "P",
    "title": "Anggota"
  },
  {
    "nis": "6",
    "name": "cantika khumairah putri",
    "gender": "P",
    "title": "Anggota"
  },
  {
    "nis": "7",
    "name": "christian octavianus simamora",
    "gender": "L",
    "title": "Anggota"
  },
  {
    "nis": "8",
    "name": "christopher yansen hagai tiwow",
    "gender": "L",
    "title": "Anggota"
  },
  {
    "nis": "9",
    "name": "cindy",
    "gender": "P",
    "title": "akomodasi"
  },
  {
    "nis": "10",
    "name": "claresta",
    "gender": "P",
    "title": "Anggota"
  },
  {
    "nis": "11",
    "name": "elin",
    "gender": "P",
    "title": "Anggota"
  },
  {
    "nis": "12",
    "name": "althaf",
    "gender": "L",
    "title": "Anggota"
  },
  {
    "nis": "13",
    "name": "echa",
    "gender": "P",
    "title": "Anggota"
  },
  {
    "nis": "14",
    "name": "ellen",
    "gender": "P",
    "title": "Anggota"
  },
  {
    "nis": "15",
    "name": "vanya",
    "gender": "P",
    "title": "Anggota"
  },
  {
    "nis": "16",
    "name": "dony",
    "gender": "L",
    "title": "Anggota"
  },
  {
    "nis": "17",
    "name": "juan",
    "gender": "L",
    "title": "Anggota"
  },
  {
    "nis": "18",
    "name": "aurel",
    "gender": "P",
    "title": "Anggota"
  },
  {
    "nis": "19",
    "name": "arsyad",
    "gender": "L",
    "title": "Anggota"
  },
  {
    "nis": "20",
    "name": "azzam",
    "gender": "L",
    "title": "wakil ketua kelas"
  },
  {
    "nis": "21",
    "name": "melany",
    "gender": "P",
    "title": "Anggota"
  },
  {
    "nis": "22",
    "name": "ilham",
    "gender": "L",
    "title": "bendahara 2"
  },
  {
    "nis": "23",
    "name": "reza",
    "gender": "L",
    "title": "Anggota"
  },
  {
    "nis": "24",
    "name": "zaghlul",
    "gender": "L",
    "title": "Anggota"
  },
  {
    "nis": "25",
    "name": "mukhlis",
    "gender": "L",
    "title": "Anggota"
  },
  {
    "nis": "26",
    "name": "aqilla",
    "gender": "P",
    "title": "Anggota"
  },
  {
    "nis": "27",
    "name": "natalia",
    "gender": "P",
    "title": "sekertaris"
  },
  {
    "nis": "28",
    "name": "naura",
    "gender": "P",
    "title": "Anggota"
  },
  {
    "nis": "29",
    "name": "putri",
    "gender": "P",
    "title": "Anggota"
  },
  {
    "nis": "30",
    "name": "jesse",
    "gender": "L",
    "title": "Anggota"
  },
  {
    "nis": "31",
    "name": "caca",
    "gender": "P",
    "title": "bendahara"
  },
  {
    "nis": "32",
    "name": "sofi",
    "gender": "P",
    "title": "Anggota"
  }
]